honeyhive_logger/__init__.py
honeyhive_logger/logger.py
honeyhive_logger-0.0.11.dist-info/LICENSE
honeyhive_logger-0.0.11.dist-info/METADATA
honeyhive_logger-0.0.11.dist-info/WHEEL
honeyhive_logger-0.0.11.dist-info/top_level.txt
honeyhive_logger-0.0.11.dist-info/RECORD
