Metadata-Version: 2.1
Name: honeyhive-logger
Version: 0.0.11
Summary: A Python logger for HoneyHive
Home-page: https://github.com/honeyhive-ai/honeyhive-logger
Author: HoneyHive
Author-email: support@honeyhive.ai
Classifier: Programming Language :: Python :: 3
Classifier: License :: OSI Approved :: MIT License
Classifier: Operating System :: OS Independent
Requires-Python: >=3.7
License-File: LICENSE
Provides-Extra: dev
Requires-Dist: pytest>=7.0.0; extra == "dev"
Requires-Dist: twine>=4.0.0; extra == "dev"
